gitargus/__init__.py
gitargus/__main__.py
gitargus/core.py
gitargus-1.0.0b1.dist-info/LICENSE
gitargus-1.0.0b1.dist-info/METADATA
gitargus-1.0.0b1.dist-info/WHEEL
gitargus-1.0.0b1.dist-info/top_level.txt
gitargus-1.0.0b1.dist-info/RECORD
