Metadata-Version: 2.1
Name: gitargus
Version: 1.0.0b1
Summary: Helps avoiding conflicts for git repositories when using multiple computers.
Author-email: Balázs Klement <dev@bklement.com>
Project-URL: Homepage, https://github.com/bklement/gitargus
Project-URL: Bug Tracker, https://github.com/bklement/gitargus/issues
Classifier: Programming Language :: Python :: 3 :: Only
Classifier: License :: OSI Approved :: MIT License
Classifier: Operating System :: Unix
Classifier: Development Status :: 3 - Alpha
Requires-Python: >=3.7
License-File: LICENSE
Requires-Dist: pyyaml
Requires-Dist: boto3
Requires-Dist: pytz
